ckanext_flakes-0.5.0-py3.9-nspkg.pth
ckanext/flakes/__init__.py
ckanext/flakes/config_declaration.yaml
ckanext/flakes/interfaces.py
ckanext/flakes/plugin.py
ckanext/flakes/types.py
ckanext/flakes/logic/__init__.py
ckanext/flakes/logic/action.py
ckanext/flakes/logic/auth.py
ckanext/flakes/logic/schema.py
ckanext/flakes/logic/validators.py
ckanext/flakes/migration/flakes/alembic.ini
ckanext/flakes/migration/flakes/env.py
ckanext/flakes/migration/flakes/script.py.mako
ckanext/flakes/migration/flakes/versions/a7384c7e0e27_nullable_author.py
ckanext/flakes/migration/flakes/versions/b8a5f5419306_create_flake_table.py
ckanext/flakes/model/__init__.py
ckanext/flakes/model/base.py
ckanext/flakes/model/flake.py
ckanext/flakes/plugins/__init__.py
ckanext/flakes/plugins/scheming.py
ckanext/flakes/plugins/feedback/__init__.py
ckanext/flakes/plugins/feedback/config_declaration.yaml
ckanext/flakes/plugins/feedback/plugin.py
ckanext/flakes/plugins/feedback/views.py
ckanext/flakes/plugins/feedback/assets/webassets.yml
ckanext/flakes/plugins/feedback/logic/__init__.py
ckanext/flakes/plugins/feedback/logic/action.py
ckanext/flakes/plugins/feedback/logic/auth.py
ckanext/flakes/plugins/feedback/logic/schema.py
ckanext/flakes/plugins/feedback/templates/flakes_feedback/delete.html
ckanext/flakes/plugins/feedback/templates/flakes_feedback/index.html
ckanext/flakes/plugins/feedback/templates/flakes_feedback/post.html
ckanext/flakes/plugins/feedback/templates/package/read_base.html
ckanext/flakes/plugins/rating/__init__.py
ckanext/flakes/plugins/rating/config.py
ckanext/flakes/plugins/rating/config_declaration.yaml
ckanext/flakes/plugins/rating/helpers.py
ckanext/flakes/plugins/rating/plugin.py
ckanext/flakes/plugins/rating/assets/flakes-rating-rate.js
ckanext/flakes/plugins/rating/assets/webassets.yml
ckanext/flakes/plugins/rating/logic/__init__.py
ckanext/flakes/plugins/rating/logic/action.py
ckanext/flakes/plugins/rating/logic/auth.py
ckanext/flakes/plugins/rating/logic/schema.py
ckanext_flakes-0.5.0.dist-info/LICENSE
ckanext_flakes-0.5.0.dist-info/METADATA
ckanext_flakes-0.5.0.dist-info/WHEEL
ckanext_flakes-0.5.0.dist-info/entry_points.txt
ckanext_flakes-0.5.0.dist-info/namespace_packages.txt
ckanext_flakes-0.5.0.dist-info/top_level.txt
ckanext_flakes-0.5.0.dist-info/RECORD
